{
  "cached_at": "2026-05-04T08:02:11.160592+00:00",
  "data": {
    "url": "https://www.ft.com/content/5a92811f-bd14-4be3-8b77-5edc12461cf5?syn-25a6b1a6=1",
    "title": "Saudi Arabia touts new use for Neom port after Iran war",
    "description": "With the Strait of Hormuz choked off, Riyadh focuses on Red Sea infrastructure",
    "image": "https://images.ft.com/v3/image/raw/https%3A%2F%2Fd1e00ek4ebabms.cloudfront.net%2Fproduction%2F196802b8-a0bb-466c-802c-1ed4ab226ebc.jpg?source=next-barrier-page",
    "favicon": "https://images.ft.com/v3/image/raw/ftlogo-v1%3Abrand-ft-logo-square-coloured?source=page-kit&format=png&width=180&height=180",
    "site_name": null,
    "author": null,
    "keywords": null
  }
}