{
  "cached_at": "2026-05-07T16:03:15.290816+00:00",
  "data": {
    "url": "https://www.nytimes.com/2026/05/07/business/shell-profit-oil-iran-war.html",
    "title": "Shell Reports Nearly $7 Billion Profit After Oil Prices Surged Amid U.S.-Iran War",
    "description": "The oil giant\u2019s earnings in the first three months of the year were more than double the previous quarter\u2019s and follow similarly strong results of European rivals.",
    "image": "https://static01.nyt.com/images/2026/05/07/multimedia/07BIZ-shell-tkqc/07BIZ-shell-tkqc-facebookJumbo.jpg",
    "favicon": "https://www.nytimes.com/vi-assets/static-assets/apple-touch-icon-28865b72953380a40aa43318108876cb.png",
    "site_name": null,
    "author": null,
    "keywords": null
  }
}